llama_index/readers/obsidian/__init__.py
llama_index/readers/obsidian/base.py
llama_index_readers_obsidian-0.6.1.dist-info/METADATA
llama_index_readers_obsidian-0.6.1.dist-info/WHEEL
llama_index_readers_obsidian-0.6.1.dist-info/licenses/LICENSE
llama_index_readers_obsidian-0.6.1.dist-info/RECORD
